spectranorm/__init__.py
spectranorm/data/templates/CIFTI/ones.dscalar.nii
spectranorm/data/templates/HCP/S1200.L.midthickness_MSMAll.32k_fs_LR.surf.gii
spectranorm/data/templates/HCP/S1200.R.midthickness_MSMAll.32k_fs_LR.surf.gii
spectranorm/data/templates/fs_LR_32k/fs_LR-deformed_to-fsaverage.L.sphere.32k_fs_LR.surf.gii
spectranorm/data/templates/fs_LR_32k/fs_LR-deformed_to-fsaverage.R.sphere.32k_fs_LR.surf.gii
spectranorm/py.typed
spectranorm/snm.py
spectranorm/utils/__init__.py
spectranorm/utils/general.py
spectranorm/utils/gsp.py
spectranorm/utils/metrics.py
spectranorm/utils/nitools.py
spectranorm/utils/parallel.py
spectranorm/utils/stats.py
spectranorm-0.1.1.dist-info/LICENSE
spectranorm-0.1.1.dist-info/METADATA
spectranorm-0.1.1.dist-info/WHEEL
spectranorm-0.1.1.dist-info/RECORD
