Metadata-Version: 2.3
Name: spectranorm
Version: 0.1.1
Summary: A Python package for spectral normative modeling of neuroimaging and other high-dimensional data.
License: Dual license: AGPLv3 for non-commercial use; proprietary commercial license available. See LICENSE file for details.
Author: Sina Mansour L.
Author-email: sina.mansour.lakouraj@gmail.com
Requires-Python: >=3.10,<3.14
Classifier: Development Status :: 4 - Beta
Classifier: Intended Audience :: Developers
Classifier: Intended Audience :: Healthcare Industry
Classifier: Intended Audience :: Science/Research
Classifier: License :: Other/Proprietary License
Classifier: Operating System :: OS Independent
Classifier: Programming Language :: Python
Classifier: Programming Language :: Python :: 3
Classifier: Programming Language :: Python :: 3.10
Classifier: Programming Language :: Python :: 3.11
Classifier: Programming Language :: Python :: 3.12
Classifier: Programming Language :: Python :: 3.13
Classifier: Topic :: Scientific/Engineering :: Artificial Intelligence
Classifier: Topic :: Scientific/Engineering :: Medical Science Apps.
Classifier: Topic :: Software Development :: Libraries :: Python Modules
Classifier: Typing :: Typed
Requires-Dist: arviz (>=0.21)
Requires-Dist: joblib (>=1.5)
Requires-Dist: nibabel (>=5.3)
Requires-Dist: numpy (>=1.25)
Requires-Dist: pandas (>=2.2)
Requires-Dist: patsy (>=1.0)
Requires-Dist: pymc (>=5.23)
Requires-Dist: pytensor (>=2.31)
Requires-Dist: scipy (>=1.15)
Requires-Dist: tqdm (>=4.67)
Project-URL: Documentation, https://sina-mansour.github.io/spectranorm
Project-URL: Homepage, https://sina-mansour.github.io/spectranorm
Project-URL: Repository, https://github.com/sina-mansour/spectranorm
